chatbottokenizer/__init__.py
chatbottokenizer/tokenizer.py
chatbottokenizer-0.0.1.dist-info/METADATA
chatbottokenizer-0.0.1.dist-info/WHEEL
chatbottokenizer-0.0.1.dist-info/top_level.txt
chatbottokenizer-0.0.1.dist-info/RECORD
