Metadata-Version: 2.1
Name: chatbottokenizer
Version: 0.0.1
Summary: Tokenizer for chat bots
Home-page: https://github.com/t94j0/chatbot-tokenizer
Author: Max Harley
Author-email: maxh@maxh.io
License: UNKNOWN
Platform: UNKNOWN
Classifier: Programming Language :: Python :: 3
Classifier: Operating System :: OS Independent
